uProcess_x64/__init__.py
uProcess_x64/uProcess_x64.pyd
LabSmith_uProcess_x64-3.10.1.1.dist-info/METADATA
LabSmith_uProcess_x64-3.10.1.1.dist-info/WHEEL
LabSmith_uProcess_x64-3.10.1.1.dist-info/top_level.txt
LabSmith_uProcess_x64-3.10.1.1.dist-info/RECORD
