Metadata-Version: 2.1
Name: LabSmith-uProcess-x64
Version: 3.10.1.1
Summary: Python x64 support for controlling LabSmith uDevices
Home-page: http://www.labsmith.com
Author: LabSmith
Author-email: ecummings@labsmith.com
License: UNKNOWN
Platform: UNKNOWN
Classifier: Programming Language :: Python :: 3
Classifier: License :: OSI Approved :: MIT License
Classifier: Operating System :: Microsoft :: Windows
Classifier: Natural Language :: English
Requires-Python: ==3.10
